docere/__init__.py
docere/__main__.py
docere/cli.py
docere/render.py
docere/plugins/__init__.py
docere/plugins/index/__init__.py
docere/plugins/index/skeleton/LICENSE.md
docere/plugins/index/skeleton/README.md
docere/plugins/index/skeleton/bower.json
docere/plugins/index/skeleton/index.html
docere/plugins/index/skeleton/css/normalize.css
docere/plugins/index/skeleton/css/skeleton.css
docere/plugins/index/skeleton/images/favicon.png
docere/plugins/index/templates/body.html
docere/plugins/index/templates/index.html
docere-0.9.dist-info/METADATA
docere-0.9.dist-info/WHEEL
docere-0.9.dist-info/entry_points.txt
docere-0.9.dist-info/top_level.txt
docere-0.9.dist-info/RECORD
